hydra_once/__init__.py
hydra_once/_instantiate.py
hydra_once/_once.py
hydra_once-0.1.0.dist-info/METADATA
hydra_once-0.1.0.dist-info/WHEEL
hydra_once-0.1.0.dist-info/top_level.txt
hydra_once-0.1.0.dist-info/RECORD
