Metadata-Version: 2.1
Name: hydra-once
Version: 0.1.0
Summary: A simple library for use with Hydra or OmegaConf configuration, enabling singleton instantiation of config subtrees.
Author-email: "S. Joshua Swamidass" <swamidass@gmail.com>
License: MIT
Project-URL: Homepage, https://github.com/swamidass/hydra-once
Project-URL: Repository, https://github.com/swamidass/hydra-once
Keywords: hydra,omegaconf,configuration,singleton,instantiation
Classifier: Development Status :: 4 - Beta
Classifier: Intended Audience :: Developers
Classifier: License :: OSI Approved :: MIT License
Classifier: Operating System :: OS Independent
Classifier: Programming Language :: Python :: 3
Classifier: Programming Language :: Python :: 3.8
Classifier: Programming Language :: Python :: 3.9
Classifier: Programming Language :: Python :: 3.10
Classifier: Programming Language :: Python :: 3.11
Classifier: Programming Language :: Python :: 3.12
Classifier: Topic :: Software Development :: Libraries :: Python Modules
Classifier: Topic :: Utilities
Requires-Python: >=3.8
Requires-Dist: hydra-core >=1.3.2
Requires-Dist: omegaconf >=2.1
Provides-Extra: dev
Requires-Dist: pytest >=8.3.5 ; extra == 'dev'
